AUTHORS.rst
CHANGELOG.rst
INSTALL.rst
LICENSE.rst
MANIFEST.in
README.rst
TODO.rst
setup.cfg
setup.py
docs/api-objects.txt
docs/class-tree.html
docs/crarr.png
docs/epydoc.css
docs/epydoc.js
docs/exceptions.AssertionError-class.html
docs/frames.html
docs/help.html
docs/identifier-index.html
docs/index.html
docs/module-tree.html
docs/pushnotify-module.html
docs/pushnotify-pysrc.html
docs/pushnotify._version-module.html
docs/pushnotify._version-pysrc.html
docs/pushnotify.abstract-module.html
docs/pushnotify.abstract-pysrc.html
docs/pushnotify.abstract.AbstractClient-class.html
docs/pushnotify.exceptions-module.html
docs/pushnotify.exceptions-pysrc.html
docs/pushnotify.exceptions.ApiKeyError-class.html
docs/pushnotify.exceptions.FormatError-class.html
docs/pushnotify.exceptions.PermissionDenied-class.html
docs/pushnotify.exceptions.ProviderKeyError-class.html
docs/pushnotify.exceptions.PushNotifyError-class.html
docs/pushnotify.exceptions.RateLimitExceeded-class.html
docs/pushnotify.exceptions.ServerError-class.html
docs/pushnotify.exceptions.UnknownError-class.html
docs/pushnotify.exceptions.UnrecognizedResponseError-class.html
docs/pushnotify.nma-module.html
docs/pushnotify.nma-pysrc.html
docs/pushnotify.nma.Client-class.html
docs/pushnotify.prowl-module.html
docs/pushnotify.prowl-pysrc.html
docs/pushnotify.prowl.Client-class.html
docs/pushnotify.pushover-module.html
docs/pushnotify.pushover-pysrc.html
docs/pushnotify.pushover.Client-class.html
docs/pushnotify.tests-module.html
docs/pushnotify.tests-pysrc.html
docs/pushnotify.tests.tests-module.html
docs/pushnotify.tests.tests-pysrc.html
docs/pushnotify.tests.tests.AbstractClientTest-class.html
docs/pushnotify.tests.tests.NMATest-class.html
docs/pushnotify.tests.tests.ProwlTest-class.html
docs/pushnotify.tests.tests.PushnotifyTest-class.html
docs/pushnotify.tests.tests.PushoverTest-class.html
docs/redirect.html
docs/toc-everything.html
docs/toc-pushnotify-module.html
docs/toc-pushnotify._version-module.html
pushnotify.egg-info/PKG-INFO
pushnotify.egg-info/SOURCES.txt
pushnotify.egg-info/dependency_links.txt
pushnotify.egg-info/requires.txt
pushnotify.egg-info/top_level.txt
