Metadata-Version: 1.1
Name: pushnotify
Version: 0.5.1
Summary: A package for sending push notifications to Android and iOS devices.
Home-page: https://bitbucket.org/jgoettsch/py-pushnotify/
Author: Jeffrey Goettsch
Author-email: jgoettsch+pypushnotify@gmail.com
License: UNKNOWN
Download-URL: https://bitbucket.org/jgoettsch/py-pushnotify/get/0.5.1.tar.gz
Platform: UNKNOWN
Classifier: Development Status :: 5 - Production/Stable
Classifier: Intended Audience :: Developers
Classifier: Intended Audience :: System Administrators
Classifier: License :: OSI Approved :: GNU General Public License v3 or later (GPLv3+)
Classifier: Operating System :: OS Independent
Classifier: Programming Language :: Python
Classifier: Programming Language :: Python :: 2
Classifier: Topic :: Software Development
Classifier: Topic :: Software Development :: Libraries
Classifier: Topic :: Software Development :: Libraries :: Python Modules
Classifier: Topic :: System :: Monitoring
Classifier: Topic :: System :: Systems Administration
